{
  "location": "Diễn kỳ, Diễn Châu",
  "establishment": "1992",
  "category": "Lịch sử",
  "relatedCharacters": {
    "Ngô Trí Vinh": null,
    "Trịnh Cảnh Thuỵ": null,
    "Ngô Phương Lan": null,
    "Lê Thần Tông": 1930,
    "Ngô Trí Hoà": null,
    "Phan Huy Chú": 1395,
    "Lê Thế Tông": 314,
    "Ngô Trí Tri": 1451,
    "Ngô Công Định": null
  },
  "id": 1568,
  "entityName": "Đền thờ và mộ Ngô Trí Hòa",
  "aliases": [],
  "overview": "Ngô Trí Hòa (1564-1625) là danh thần nhà Lê trung hưng trong lịch sử Việt Nam. Tên tuổi của ông không chỉ được ghi trong sử sách mà còn được biết đến qua các văn học dân gian Việt Nam."
}