{
  "dateOfBirth": "Không rõ",
  "dateOfDeath": "Không rõ",
  "hometown": "Không rõ",
  "occupation": "Không rõ",
  "workTenure": "Không rõ",
  "fatherName": {},
  "motherName": {},
  "eraName": {},
  "id": 1163,
  "entityName": "Vũ Hán",
  "aliases": [],
  "overview": "Vũ Hán (tiếng Hoa giản thể: 武汉; tiếng Hoa phồn thể: 武漢; pinyin: Wǔhàn; phát âm: Wuhan ) là thủ phủ của tỉnh Hồ Bắc, Trung Quốc. Đây là thành phố đông dân nhất ở miền Trung Trung Quốc. Thành phố nằm ở ngã ba sông Dương Tử và sông Hán (Hán Thủy), là trung tâm vận tải chính với hàng loạt tuyến đường sắt, đường bộ và đường cao tốc nối với các thành phố lớn trong Trung Quốc đại lục. Vì có vị trí then chốt trong giao thông nội địa, Vũ Hán được đặt tên \"Chicago của Trung Quốc\"."
}