{
  "dateOfBirth": "18 tháng 6 năm 1907 Hải Dương, Liên bang Đông Dương",
  "dateOfDeath": "4 tháng 6, 2009 (101 tuổi) Thành phố Hồ Chí Minh, Việt Nam",
  "hometown": "quê Hải Dương ,tên thật là Vũ An Tuyết , là một nghệ sĩ nhiếp ảnh nổi tiếng của Việt Nam.",
  "occupation": "Không rõ",
  "workTenure": "Không rõ",
  "fatherName": {},
  "motherName": {},
  "eraName": {},
  "id": 102,
  "entityName": "Võ An Ninh",
  "aliases": [
    "Vũ An Tuyết"
  ],
  "overview": "Võ An Ninh (18 tháng 6 năm 1907 – 4 tháng 6 năm 2009), quê Hải Dương ,tên thật là Vũ An Tuyết , là một nghệ sĩ nhiếp ảnh nổi tiếng của Việt Nam. Ông sở hữu nhiều bộ ảnh có giá trị của lịch sử Việt Nam. Ông từng làm phóng viên nhiếp ảnh Sở Kiểm lâm Hà Nội thời Pháp thuộc, khu Triển lãm Trung ương và Xưởng phim Đèn chiếu Việt Nam (1954 - 1970), ủy viên Ủy ban Trung ương Hội Liên hiệp Văn học Nghệ thuật Việt Nam, ủy viên Hội đồng Nghệ thuật Hội Nghệ sĩ Nhiếp ảnh Việt Nam khóa 3."
}