{
  "dateOfBirth" : "Không rõ",
  "dateOfDeath" : "1428",
  "hometown" : "xã Nhuệ Chiết, huyện Ma Khê, phủ Tam Giang, thuộc tỉnh Bắc Giang, Việt Nam.",
  "occupation" : "Không rõ",
  "workTenure" : "Không rõ",
  "fatherName" : { },
  "motherName" : { },
  "eraName" : { },
  "id" : 1296,
  "entityName" : "Đỗ Duy Trung",
  "aliases" : [ ],
  "overview" : "Đỗ Duy Trung (杜維忠, ?-1428) là tướng người Việt hợp tác với quân Minh thời kỳ Bắc thuộc lần thứ tư trong lịch sử Việt Nam. Theo sách Đại Việt thông sử, Đỗ Duy Trung người xã Nhuệ Chiết, huyện Ma Khê, phủ Tam Giang, thuộc tỉnh Bắc Giang, Việt Nam."
}