{
  "dateOfBirth": "Canh Dần 1890",
  "dateOfDeath": "Canh Tuất 1910",
  "hometown": "quê phủ Hưng Nguyên, tỉnh Nghệ An",
  "occupation": "Nhà yêu nước ",
  "workTenure": "Không rõ",
  "fatherName": {},
  "motherName": {},
  "eraName": {
    "Pháp đô hộ": 11
  },
  "id": 2131,
  "entityName": "Phan Lại Lượng",
  "aliases": [],
  "overview": "Ông tích cực hưởng ứng phong trào Đông du, Duy tân. Năm Mậu thân 1908 ông vừa 18 tuổi, cha mẹ ép cưới vợ cho ông, chưa được hai tháng, ông thoát li gia đình, cùng với Nguyễn Đức Công (tức Hoàng Trọng Mậu) và một nhóm 15 thanh niên dò đường núi sang Quảng Tây rồi đi Nhật, đến Đông Kinh được tổ chức đưa vào học ở Đồng văn thư viện. Ít lâu, ông lâm bệnh nhưng vẫn cố gắng học tập. Sau, ông trở về Hương Cảng, bệnh thêm nặng, 1910 ông xuống tàu đi Quảng Đông, phẫn chí vì bệnh không thuyên giảm, không đạt thành được nguyện vọng, ông nhảy xuống biển tự tử. Các thủy thủ cứu lên đưa vào y viện, nhưng không còn cứu được nữa. Ông mất, hưởng dương 20 tuổi. Trần Quốc Duy điếu ông: \"Phù sinh hà tác bi, khả liên quốc nạn gia cừu, tráng chí bán sinh lưu thủy thệ; Đồng đảng y nhiên tại; hội khán càn khôn hoán chuyển, anh hồn vạn lí liệt phong lai.\" Nghĩa: Phù sinh có tiếc gì, đáng thương nạn nước cừu nhà, tráng chí nửa đời theo nước chảy; Đồng đảng còn đây cả sẽ thấy trời xoay đất chuyển hồn thương muôn dặm gió đưa về."
}