{
  "dateOfBirth": "Ất Mão 1795",
  "dateOfDeath": "Không rõ",
  "hometown": "quê làng Đông Ngạc, huyện Từ Liêm, tỉnh Hà Đông, ngụ cư làng Đông Ngạc, huyện Gia Bình, tỉnh Bắc Ninh",
  "occupation": "Danh thần đời Minh Mạng, sinh năm Ất mão 1795",
  "workTenure": "Không rõ",
  "fatherName": {},
  "motherName": {},
  "eraName": {
    "Nhà Nguyễn độc lập": 30
  },
  "id": 246,
  "entityName": "Hoàng Tế Mĩ",
  "aliases": [],
  "overview": "Ông là con tiến sĩ Lê Xuân Thự, và là thân phụ của tiến sĩ Hoàng Tướng Hiệp. Năm Ất dậu 1825, ông đỗ giải nguyên; năm sau Bính tuất 1826 đỗ nhị giáp tiến sĩ 31 tuổi. Làm quan đến Tham tri bộ Binh, rồi đổi sang bộ Lại. Đến đời Tự Đức, được tham dự ở tòa Kinh Diên và Viện Cơ mật, Viện Hàn lâm. Có đi sứ nhà Thanh, ông làm chánh sứ, được người Trung Quốc kính nể. Lúc mất, được tặng Thượng thư bộ Lễ"
}