{
  "dateOfBirth" : "Ất Mão 1915",
  "dateOfDeath" : "Ất Hợi 1995",
  "hometown" : "quê làng Vân Đình, huyện Sơn Lăng, phủ Ứng Hòa, tỉnh Hà Đông (nay thuộc tỉnh Hà Tây)",
  "occupation" : "Nhạc sĩ hiện đại",
  "workTenure" : "Không rõ",
  "fatherName" : { },
  "motherName" : { },
  "eraName" : {
    "Nước Việt Nam mới" : 29
  },
  "id" : 2738,
  "entityName" : "Dương Thiêu Tước",
  "aliases" : [ ],
  "overview" : "Xuất thân trong gia đình Nho học truyền thống, cháu nội cụ nghè Vân Đình Dương Khuê, nguyên Đốc học Nam Định. Thuở nhỏ học ở Hà Nội, những năm 30 ông gia nhập nhóm nghệ sĩ tài tử Myosotis (Hoa Lưu li) gồm Thẩm Oánh, Lê Yên, Doãn Mẫn, Vũ Khanh... Dương Thiệu tước là người có sáng kiến soạn các nhạc phẩm thuộc loại bài Tây theo điệu ta. Phần lớn nhạc của ông lúc đầu đều bằng tiếng Pháp đó là một thể loại đầu tiên ở nước ta và chính nó đã mở ra một hướng mới cho nền tân nhạc Việt Nam. Những nhạc phẩm: Vầng trăng sáng, Thuyền mơ, Bến xuân xanh, Dưới nắng hồng... của ông mới ra đời được giới yêu nhạc đón chào nồng nhiệt. Từ đó nét nhạc ông càng ngày càng đượm hương sắc dân tộc giúp nhạc hiện đại Việt Nam càng bay bổng trên vòm trời âm nhạc mới. Những năm sau chiến tranh Việt Pháp và hòa bình được tái lập (1954), ông vẫn tiếp tục sáng tác đều tay, như Tiếng xưa, Đêm tàn bến Ngự, Ơn nghĩa sinh thành, Ngọc Lan, Uớc hẹn chiều thu, Cánh bằng lướt gió, Trời xanh thẳm, Chiều. Tác phẩm của Dương Thiệu Tước sẽ sống mãi với lịch sử âm nhạc Việt Nam vì nhạc ông \"là loại nhạc tình tứ, nhưng rất sang trọng. Đó là những ca khúc tình ái, thốt lên từ con tim của một nhạc sĩ dòng dõi nhà quan\". Ông mất ngày 1 tháng 8 năm 1995 tại Sài Gòn, thọ 80 tuổi."
}