{
  "dateOfBirth" : "…",
  "dateOfDeath" : "Kỉ Dậu 1969",
  "hometown" : "quê làng Thủ Thiêm quận Thủ Đức, tỉnh Gia Định (nay thuộc Quận 2 Thành Phố Hồ Chí Minh) không rõ năm sinh",
  "occupation" : "Liệt sĩ hiện đại",
  "workTenure" : "Không rõ",
  "fatherName" : { },
  "motherName" : { },
  "eraName" : {
    "Nước Việt Nam mới" : 29
  },
  "id" : 2757,
  "entityName" : "Nguyễn Thị Tần",
  "aliases" : [ "Hai Phụng" ],
  "overview" : "Bà tham gia hoạt động cách mạng từ lúc còn thanh niên, đảng viên đảng cộng sản Việt Nam. Năm 1966 được bầu làm Quận ủy viên Quận 2 (cũ), bị địch bắt giam tại nhà tù Thủ Đức, tỉnh Gia Định. Trong tù bà bị tra tấn cực hình, nhưng bà vẫn không khai báo, nên bảo toàn được các cơ sở do bà lãnh đạo. Bà hi sinh ngày 22-8-1969 tại Thủ Đức."
}