{
  "dateOfBirth": "175",
  "dateOfDeath": "219",
  "hometown": "Không rõ",
  "occupation": "Không rõ",
  "workTenure": "Không rõ",
  "fatherName": {},
  "motherName": {},
  "eraName": {},
  "id": 658,
  "entityName": "Dương Tu",
  "aliases": [
    "Đức Tổ"
  ],
  "overview": "Dương Tu (chữ Hán: 杨修; 175 - 219), biểu tự Đức Tổ (德祖), là một mưu sĩ của Tào Ngụy, phục vụ dưới trướng của Tào Tháo, về sau đi theo trợ giúp con thứ tư của Tào Tháo là Tào Thực trong giai đoạn tranh ngôi vị Thế tử giữa anh em Tào Phi cùng Tào Xung và Tào Chương."
}