{
  "dateOfBirth": "Giáp Tuất 1874",
  "dateOfDeath": "Nhâm Thân 1932",
  "hometown": "Hà Nội",
  "occupation": "Doanh nhân lừng tiếng ở Bắc kì, nhất là về mặt hàng hải, tranh thương cùng tư sản Pháp, tư sản Trung Quốc.",
  "workTenure": "Không rõ",
  "fatherName": {},
  "motherName": {},
  "eraName": {
    "Pháp đô hộ": 11
  },
  "id": 73,
  "entityName": "Bạch Thái Bưởi",
  "aliases": [],
  "overview": "Ông quê làng An Phúc, tỉnh Hà Đông (nay là TP. Hà Nội). Vốn là họ Đỗ, nhà nghèo, cha mất sớm, phải giúp đỡ mẹ sinh nhai bằng nghề bán hàng rong. Nhờ một người nhà giàu họ Bạch nuôi làm con, mới đổi ra họ Bạch, cho ăn học khá giỏi. Năm 21 tuổi, ông làm thư kí cho một hãng buôn của người Pháp, tục gọi kí Năm. Ít lâu, ông đứng ra kinh doanh, đáng kể là việc mở nhà in lớn ở Hà Nội mang tên Đông Kinh ấn quán, sau nhượng lại cho người em rể là Lê Văn Phúc quản lí. Rồi từ năm 1909, ông bước vào lĩnh vực thương thuyền, hàng hải, trở nên một nhà tư sản nổi tiếng và được giới tư sản đương thời tặng biệt danh là Chúa sông miền Bắc. Trong vòng 10 năm, Công ty Bạch Thái Bưởi có đến trên 30 chiếc tàu lớn nhỏ, mang những tên: Phi Long, Phi Phượng, Phi Hổ, Yên Bái, Phố La, Bảo Hà, Chợ Bờ và những tên lịch sử: Hồng Bàng, Lạc Long, Trưng Nhi, Đinh Tiên Hoàng, Lê Lợi, Gia Long, Tự Đức... có thể cạnh tranh cùng tư sản thương thuyền Pháp. Đến năm Mậu thân 1932, ông mất, mộ táng ở vùng mỏ Đông Triều, nơi ông đã từng khai thác mỏ than. Khi Bạch Thái Bưởi mất, Ưng Hòe Nguyễn Văn Tố viết trong tạp chí Đông Thanh cho ông là: \"Bậc anh hùng kinh tế thứ nhất trong kinh tế giới nước nhà\"."
}