{
  "dateOfBirth" : "sinh năm 1920",
  "dateOfDeath" : "Không rõ",
  "hometown" : "Không rõ",
  "occupation" : "Không rõ",
  "workTenure" : "Không rõ",
  "fatherName" : { },
  "motherName" : { },
  "eraName" : { },
  "id" : 945,
  "entityName" : "Đặng Văn Việt",
  "aliases" : [ ],
  "overview" : "Đặng Văn Việt (sinh năm 1920) là một cựu trung tá Quân đội Nhân dân Việt Nam. Ông nguyên là trung đoàn trưởng đầu tiên của Trung đoàn 174 - một trong 3 trung đoàn chủ lực đầu tiên của Quân đội Nhân dân Việt Nam. Ông từng được người Pháp mệnh danh là \"Con hùm xám đường số 4\" do thành tích chỉ huy đơn vị mình trong Chiến dịch Biên giới thu đông 1950, bắt sống cả hai chỉ huy binh đoàn Pháp là các Trung tá Marcel Lepage và Pierre Charton."
}