{
  "location": "Huyện Cát Hải, thành phố Hải Phòng 20°50′0″B 107°00′0″Đ﻿ / ﻿20,83333°B 107°Đ﻿ / 20.83333; 107.00000",
  "establishment": "Không rõ",
  "category": "Danh lam thắng cảnh",
  "relatedCharacters": {},
  "id": 1312,
  "entityName": "Quần đảo Cát Bà",
  "aliases": [],
  "overview": "Quần đảo Cát Bà là một quần đảo gồm 367 đảo, trong đó có đảo Cát Bà ở phía nam vịnh Hạ Long, ngoài khơi thành phố Hải Phòng và tỉnh Quảng Ninh, cách trung tâm thành phố Hải Phòng khoảng 30 km, cách thành phố Hạ Long khoảng 25 km. Về mặt hành chính, quần đảo thuộc huyện Cát Hải, thành phố Hải Phòng. Nơi đây đã được UNESCO công nhận là khu dự trữ sinh quyển thế giới. Cơ sở hạ tầng khá phát triển với tổ hợp nhiều khách sạn, nhà nghỉ, khu nghỉ dưỡng, chùa chiền và đặc biệt là toàn bộ khu vực đảo đã được thành phố Hải Phòng triển khai các trạm thu phát sóng vô tuyến (Wifi). Cát Bà đang không ngừng được đầu tư và phát triển để trở thành địa điểm du lịch mang tầm vóc quốc tế trong tương lai."
}