{
  "location": "Bình Minh, Thanh Oai",
  "establishment": "1992",
  "category": "Lịch sử văn hóa",
  "relatedCharacters": {
    "Đỗ Cảnh Công": null,
    "Đế Minh": null,
    "Đỗ Cảnh Thạch": null,
    "Đỗ Cảnh Thạc": 627,
    "Đỗ Cảnh Thạctrồng": null,
    "Phạm Văn Đồng": 657,
    "Viêm Đế Thần Nông": null,
    "Lý Thái Tông": 1268,
    "Lã Xử Bình": null
  },
  "id": 1563,
  "entityName": "Đình Ngoại Bình Đà",
  "aliases": [],
  "overview": "Bình Đà là một làng Việt cổ. Thuộc xã Bình Minh, huyện Thanh Oai, thành phố Hà Nội, Việt Nam."
}