{
  "location": "Bùi Hữu Nghĩa, Bình Thủy",
  "establishment": "25/1/1994",
  "category": "Lịch sử văn hóa",
  "relatedCharacters": {
    "Tú Văn Bình": null,
    "Nguyễn Văn Lý": null,
    "Phan Thanh Giản": 2681,
    "Lê Khánh Trinh": null,
    "Thạch Võ Hà": null,
    "Tống Văn Uyển": null,
    "Nguyễn Thị Tồn": null,
    "Bùi Hữu Vị": null,
    "Phan Văn Trị": 1386,
    "Nguyễn Hiển Dĩnh": 2182,
    "Bùi Hữu Nghĩa": 820,
    "Tôn Thọ Tường": 911,
    "Huỳnh Mẫn Đạt": 2881,
    "Trương Văn Uyển": null,
    "Nguyễn Phúc Ánh": 1894,
    "Tú Gia Định": null,
    "Bùi Quang Nghĩa": null
  },
  "id": 452,
  "entityName": "Mộ thủ khoa Bùi Hữu Nghĩa",
  "aliases": [],
  "overview": "Bùi Hữu Nghĩa (1807 - 1872), hay Thủ khoa Nghĩa, trước có tên là là Bùi Quang Nghĩa, hiệu Nghi Chi; là quan nhà Nguyễn, là nhà thơ và là nhà soạn tuồng Việt Nam."
}