{
  "location": "Quảng Nam, Việt Nam",
  "time": "Tháng 4 năm 1775",
  "result": "Quân Trịnh chiến thắng, Tây Sơn phải quy thuận",
  "relatedCharacters": {
    "Lê Quý Đôn": null,
    "Lý Tài": 3073,
    "Trương Phúc Loan": 1483,
    "Nguyễn Phúc Dương": 174,
    "Nguyễn Phúc Thuần": 2580,
    "Hoàng Đình Thể": 747,
    "Nguyễn Văn Chính": 359,
    "Nguyễn Huệ": null,
    "Hoàng Đình Bảo": 1187,
    "Hoàng Ngũ Phúc": 561,
    "Nguyễn Nghiễm": 1987,
    "Hoàng Phùng Cơ": 2944,
    "Nguyễn Đình Đống": 3005,
    "Bùi Thế Đạt": 2583,
    "Nguyễn Nhạc": 2547,
    "Nguyễn Hữu Chỉnh": 1761,
    "Trịnh Sâm": null
  },
  "id": 13,
  "entityName": "Trận Cẩm Sa",
  "aliases": [],
  "overview": "Trận Cẩm Sa là một phần của cuộc chiến tranh Tây Sơn-Chúa Trịnh vào cuối thế kỷ 18 trong lịch sử Việt Nam giữa chúa Trịnh và chính quyền Tây Sơn của Nguyễn Nhạc."
}