{
  "location": "Định Tường, Nam Kỳ",
  "time": "26 tháng 3 năm 1861 - 14 tháng 4 năm 1861",
  "result": "Quân Pháp thắng trận",
  "relatedCharacters": {
    "Phạm Văn Sơn": 787,
    "Võ Duy Dương": 2397,
    "Trần Trọng Kim": 2638,
    "Huỳnh Mẫn Đạt": 204,
    "Đỗ Trình Thoại": 1485,
    "Nguyễn Hữu Thành": 426,
    "Trần Văn Giàu": 1270,
    "Nguyễn Công Nhàn": 66,
    "Trương Định": 1993,
    "Nguyễn Bá Nghi": 1924,
    "Huỳnh Minh": 1858
  },
  "id": 21,
  "entityName": "Trận Định Tường",
  "aliases": [],
  "overview": "Trận Định Tường hay Pháp đánh chiếm Định Tường là một phần của cuộc chiến tranh Pháp-Việt 1858-1884 trong lịch sử Việt Nam, xảy ra từ ngày 26 tháng 3 năm 1861 và kết thúc vào ngày 14 tháng 4 cùng năm, tức sau khi Pháp đánh chiếm Tân Hòa (Gò Công) và làm chủ hoàn toàn tỉnh thành này."
}