{
  "dateOfBirth": "12 tháng 6, 1908 Xã Thạch Châu, huyện Lộc Hà, tỉnh Hà Tĩnh, xứ Trung Kỳ",
  "dateOfDeath": "27 tháng 4, 1979 Nhà lao Chí Hòa, thành phố Hồ Chí Minh, Việt Nam",
  "hometown": "Sài Gòn, Việt Nam Cộng hòa",
  "occupation": "Không rõ",
  "workTenure": "Không rõ",
  "fatherName": {},
  "motherName": {},
  "eraName": {},
  "id": 2470,
  "entityName": "Phan Huy Quát",
  "aliases": [
    "Châu Cử"
  ],
  "overview": "Phan Huy Quát (1908 - 1979) tự Châu Cử, nguyên quán Hà Tĩnh, là thủ tướng Việt Nam Cộng hòa từ ngày 16 tháng 2 năm 1965 đến ngày 5 tháng 6 năm 1965. Phan Huy Quát đồng thời là thành viên Đại Việt Quốc dân Đảng và Tổng trưởng Quốc phòng Quốc gia Việt Nam. Sau ngày 30 tháng 4 năm 1975, ông tổ chức vượt biên nhưng bị phát hiện, bị tuyên án tù và mất trong nhà lao Chí Hòa ngày 27 tháng 4 năm 1979."
}