{
  "time": "2/3",
  "location": "Thừa Thiên Huế, huyện Hương Trà",
  "relatedCharacters": {
    "Dinh Ngũ Vị Thánh": null,
    "Trinh Cát Viện": null,
    "Huệ Nam Điện": null,
    "Minh Kính Đài": null,
    "Am Thuỷ Phủ": null,
    "Am Trung Thiên": null,
    "Kiên Thái Vương": null,
    "Thiên Y A Na": null,
    "Am Cô Ngọc Lan": null,
    "Liễu Hạnh Công Chúa": null,
    "Đồng Khánh": 2203,
    "Hương Uyển Sơn": null
  },
  "id": 257,
  "entityName": "Lễ hội Điện Hòn Chén",
  "aliases": [],
  "overview": "Điện Hòn Chén hay Huệ Nam Điện tọa lạc trên núi Ngọc Trản, thuộc làng Ngọc Hồ, phường Hương Hồ, thành phố Huế, tỉnh Thừa Thiên Huế. Núi Ngọc Trản xưa có tên là Hương Uyển Sơn, sau mới đổi tên là Ngọc Trản (có nghĩa là chén ngọc), dân gian vẫn quen gọi là Hòn Chén vì nó có liên quan đến giai thoại về vua Minh Mạng đánh rơi chén ngọc."
}