{
  "location": "Huyện Yên Dũng, tỉnh Bắc Giang 21°12′53″B 106°19′25″Đ﻿ / ﻿21,21472°B 106,32361°Đ﻿ / 21.21472; 106.32361",
  "establishment": "Không rõ",
  "category": "Di tích lịch sử, kiến trúc nghệ thuật",
  "relatedCharacters": {
    "Lý Ôn Hoà": null,
    "Trần Minh Tông": 2061,
    "Trần Anh Tông": 2018,
    "Trần Hưng Đạo": 3128,
    "Huyền Quang Tôn Giả": null,
    "Hoàng Điều Ngự Tổ": null,
    "Trần Triều Trúc Lâm": null,
    "Trần Thái Tông": 1286,
    "Huyền Quang": 1349,
    "Hương Vân Đại Đầu": null,
    "Mạc Đĩnh Chi": 2867,
    "Lý Thần Tông": 3002
  },
  "id": 1348,
  "entityName": "Chùa Vĩnh Nghiêm",
  "aliases": [],
  "overview": "Chùa Vĩnh Nghiêm, còn được gọi là chùa Đức La, là một ngôi chùa cổ tại làng Đức La, xã Trí Yên, huyện Yên Dũng, tỉnh Bắc Giang, Việt Nam. Chùa được công nhận là một trung tâm Phật giáo, nơi đào tạo tăng đồ cho cả nước, nơi phát tích Tam Tổ phái Thiền Trúc Lâm của Phật giáo Việt Nam. Năm 2015, chùa được công nhận là Di tích quốc gia đặc biệt."
}