{
  "location": "Đức Phổ",
  "establishment": "2010",
  "category": "Lịch sử khảo cổ đặc biệt",
  "relatedCharacters": {
    "Sử Trung Hoa": null,
    "Kho Chum Sa Huỳnh": null,
    "Pô Inư Nagar": null
  },
  "id": 712,
  "entityName": "Di tích khảo cổ Văn hóa Sa Huỳnh",
  "aliases": [],
  "overview": "Văn hóa Sa Huỳnh là một nền văn hóa khảo cổ được xác định ở vào khoảng năm 1000 TCN đến cuối thế kỷ thứ 2. Nền văn hóa Sa Huỳnh là một trong ba cái nôi cổ xưa về văn minh trên lãnh thổ Việt Nam, cùng với Văn hóa Đông Sơn và Văn hóa Đồng Nai tạo thành tam giác văn hóa của Việt Nam thời kỳ đồ sắt"
}